{"nodes": [{"id": "d_office_vasp_crm_v2_app_events_ticketcommentdeleted_php", "label": "TicketCommentDeleted.php", "file_type": "code", "source_file": "D:\\office\\VASP_CRM_V2\\app\\Events\\TicketCommentDeleted.php", "source_location": "L1"}, {"id": "events_ticketcommentdeleted_ticketcommentdeleted", "label": "TicketCommentDeleted", "file_type": "code", "source_file": "D:\\office\\VASP_CRM_V2\\app\\Events\\TicketCommentDeleted.php", "source_location": "L11"}, {"id": "events_ticketcommentdeleted_ticketcommentdeleted_construct", "label": ".__construct()", "file_type": "code", "source_file": "D:\\office\\VASP_CRM_V2\\app\\Events\\TicketCommentDeleted.php", "source_location": "L22"}, {"id": "events_ticketcommentdeleted_ticketcommentdeleted_broadcaston", "label": ".broadcastOn()", "file_type": "code", "source_file": "D:\\office\\VASP_CRM_V2\\app\\Events\\TicketCommentDeleted.php", "source_location": "L31"}, {"id": "events_ticketcommentdeleted_ticketcommentdeleted_broadcastas", "label": ".broadcastAs()", "file_type": "code", "source_file": "D:\\office\\VASP_CRM_V2\\app\\Events\\TicketCommentDeleted.php", "source_location": "L41"}, {"id": "events_ticketcommentdeleted_ticketcommentdeleted_broadcastwith", "label": ".broadcastWith()", "file_type": "code", "source_file": "D:\\office\\VASP_CRM_V2\\app\\Events\\TicketCommentDeleted.php", "source_location": "L49"}], "edges": [{"source": "d_office_vasp_crm_v2_app_events_ticketcommentdeleted_php", "target": "interactswithsockets", "relation": "imports", "context": "import", "confidence": "EXTRACTED", "source_file": "D:\\office\\VASP_CRM_V2\\app\\Events\\TicketCommentDeleted.php", "source_location": "L5", "weight": 1.0}, {"source": "d_office_vasp_crm_v2_app_events_ticketcommentdeleted_php", "target": "privatechannel", "relation": "imports", "context": "import", "confidence": "EXTRACTED", "source_file": "D:\\office\\VASP_CRM_V2\\app\\Events\\TicketCommentDeleted.php", "source_location": "L6", "weight": 1.0}, {"source": "d_office_vasp_crm_v2_app_events_ticketcommentdeleted_php", "target": "shouldbroadcast", "relation": "imports", "context": "import", "confidence": "EXTRACTED", "source_file": "D:\\office\\VASP_CRM_V2\\app\\Events\\TicketCommentDeleted.php", "source_location": "L7", "weight": 1.0}, {"source": "d_office_vasp_crm_v2_app_events_ticketcommentdeleted_php", "target": "dispatchable", "relation": "imports", "context": "import", "confidence": "EXTRACTED", "source_file": "D:\\office\\VASP_CRM_V2\\app\\Events\\TicketCommentDeleted.php", "source_location": "L8", "weight": 1.0}, {"source": "d_office_vasp_crm_v2_app_events_ticketcommentdeleted_php", "target": "serializesmodels", "relation": "imports", "context": "import", "confidence": "EXTRACTED", "source_file": "D:\\office\\VASP_CRM_V2\\app\\Events\\TicketCommentDeleted.php", "source_location": "L9", "weight": 1.0}, {"source": "d_office_vasp_crm_v2_app_events_ticketcommentdeleted_php", "target": "events_ticketcommentdeleted_ticketcommentdeleted", "relation": "contains", "confidence": "EXTRACTED", "source_file": "D:\\office\\VASP_CRM_V2\\app\\Events\\TicketCommentDeleted.php", "source_location": "L11", "weight": 1.0}, {"source": "events_ticketcommentdeleted_ticketcommentdeleted", "target": "events_ticketcommentdeleted_ticketcommentdeleted_construct", "relation": "method", "confidence": "EXTRACTED", "source_file": "D:\\office\\VASP_CRM_V2\\app\\Events\\TicketCommentDeleted.php", "source_location": "L22", "weight": 1.0}, {"source": "events_ticketcommentdeleted_ticketcommentdeleted", "target": "events_ticketcommentdeleted_ticketcommentdeleted_broadcaston", "relation": "method", "confidence": "EXTRACTED", "source_file": "D:\\office\\VASP_CRM_V2\\app\\Events\\TicketCommentDeleted.php", "source_location": "L31", "weight": 1.0}, {"source": "events_ticketcommentdeleted_ticketcommentdeleted", "target": "events_ticketcommentdeleted_ticketcommentdeleted_broadcastas", "relation": "method", "confidence": "EXTRACTED", "source_file": "D:\\office\\VASP_CRM_V2\\app\\Events\\TicketCommentDeleted.php", "source_location": "L41", "weight": 1.0}, {"source": "events_ticketcommentdeleted_ticketcommentdeleted", "target": "events_ticketcommentdeleted_ticketcommentdeleted_broadcastwith", "relation": "method", "confidence": "EXTRACTED", "source_file": "D:\\office\\VASP_CRM_V2\\app\\Events\\TicketCommentDeleted.php", "source_location": "L49", "weight": 1.0}], "raw_calls": []}