{"nodes": [{"id": "d_office_vasp_crm_v2_resources_js_routes_admin_api_attendance_op_month_index_ts", "label": "index.ts", "file_type": "code", "source_file": "D:\\office\\VASP_CRM_V2\\resources\\js\\routes\\admin\\api\\attendance\\op-month\\index.ts", "source_location": "L1"}, {"id": "op_month_index_current", "label": "current()", "file_type": "code", "source_file": "D:\\office\\VASP_CRM_V2\\resources\\js\\routes\\admin\\api\\attendance\\op-month\\index.ts", "source_location": "L7"}, {"id": "op_month_index_currentform", "label": "currentForm()", "file_type": "code", "source_file": "D:\\office\\VASP_CRM_V2\\resources\\js\\routes\\admin\\api\\attendance\\op-month\\index.ts", "source_location": "L50"}, {"id": "op_month_index_resolve", "label": "resolve()", "file_type": "code", "source_file": "D:\\office\\VASP_CRM_V2\\resources\\js\\routes\\admin\\api\\attendance\\op-month\\index.ts", "source_location": "L85"}, {"id": "op_month_index_resolveform", "label": "resolveForm()", "file_type": "code", "source_file": "D:\\office\\VASP_CRM_V2\\resources\\js\\routes\\admin\\api\\attendance\\op-month\\index.ts", "source_location": "L128"}, {"id": "op_month_index_opmonth", "label": "opMonth", "file_type": "code", "source_file": "D:\\office\\VASP_CRM_V2\\resources\\js\\routes\\admin\\api\\attendance\\op-month\\index.ts", "source_location": "L158"}], "edges": [{"source": "d_office_vasp_crm_v2_resources_js_routes_admin_api_attendance_op_month_index_ts", "target": "d_office_vasp_crm_v2_resources_js_wayfinder_index_ts", "relation": "imports_from", "context": "import", "confidence": "EXTRACTED", "source_file": "D:\\office\\VASP_CRM_V2\\resources\\js\\routes\\admin\\api\\attendance\\op-month\\index.ts", "source_location": "L1", "weight": 1.0}, {"source": "d_office_vasp_crm_v2_resources_js_routes_admin_api_attendance_op_month_index_ts", "target": "wayfinder_index_queryparams", "relation": "imports", "context": "import", "confidence": "EXTRACTED", "source_file": "D:\\office\\VASP_CRM_V2\\resources\\js\\routes\\admin\\api\\attendance\\op-month\\index.ts", "source_location": "L1", "weight": 1.0}, {"source": "d_office_vasp_crm_v2_resources_js_routes_admin_api_attendance_op_month_index_ts", "target": "wayfinder_index_routequeryoptions", "relation": "imports", "context": "import", "confidence": "EXTRACTED", "source_file": "D:\\office\\VASP_CRM_V2\\resources\\js\\routes\\admin\\api\\attendance\\op-month\\index.ts", "source_location": "L1", "weight": 1.0}, {"source": "d_office_vasp_crm_v2_resources_js_routes_admin_api_attendance_op_month_index_ts", "target": "wayfinder_index_routedefinition", "relation": "imports", "context": "import", "confidence": "EXTRACTED", "source_file": "D:\\office\\VASP_CRM_V2\\resources\\js\\routes\\admin\\api\\attendance\\op-month\\index.ts", "source_location": "L1", "weight": 1.0}, {"source": "d_office_vasp_crm_v2_resources_js_routes_admin_api_attendance_op_month_index_ts", "target": "wayfinder_index_routeformdefinition", "relation": "imports", "context": "import", "confidence": "EXTRACTED", "source_file": "D:\\office\\VASP_CRM_V2\\resources\\js\\routes\\admin\\api\\attendance\\op-month\\index.ts", "source_location": "L1", "weight": 1.0}, {"source": "d_office_vasp_crm_v2_resources_js_routes_admin_api_attendance_op_month_index_ts", "target": "op_month_index_current", "relation": "contains", "confidence": "EXTRACTED", "source_file": "D:\\office\\VASP_CRM_V2\\resources\\js\\routes\\admin\\api\\attendance\\op-month\\index.ts", "source_location": "L7", "weight": 1.0}, {"source": "d_office_vasp_crm_v2_resources_js_routes_admin_api_attendance_op_month_index_ts", "target": "op_month_index_currentform", "relation": "contains", "confidence": "EXTRACTED", "source_file": "D:\\office\\VASP_CRM_V2\\resources\\js\\routes\\admin\\api\\attendance\\op-month\\index.ts", "source_location": "L50", "weight": 1.0}, {"source": "d_office_vasp_crm_v2_resources_js_routes_admin_api_attendance_op_month_index_ts", "target": "op_month_index_resolve", "relation": "contains", "confidence": "EXTRACTED", "source_file": "D:\\office\\VASP_CRM_V2\\resources\\js\\routes\\admin\\api\\attendance\\op-month\\index.ts", "source_location": "L85", "weight": 1.0}, {"source": "d_office_vasp_crm_v2_resources_js_routes_admin_api_attendance_op_month_index_ts", "target": "op_month_index_resolveform", "relation": "contains", "confidence": "EXTRACTED", "source_file": "D:\\office\\VASP_CRM_V2\\resources\\js\\routes\\admin\\api\\attendance\\op-month\\index.ts", "source_location": "L128", "weight": 1.0}, {"source": "d_office_vasp_crm_v2_resources_js_routes_admin_api_attendance_op_month_index_ts", "target": "op_month_index_opmonth", "relation": "contains", "confidence": "EXTRACTED", "source_file": "D:\\office\\VASP_CRM_V2\\resources\\js\\routes\\admin\\api\\attendance\\op-month\\index.ts", "source_location": "L158", "weight": 1.0}], "raw_calls": [{"caller_nid": "op_month_index_current", "callee": "url", "is_member_call": true, "source_file": "D:\\office\\VASP_CRM_V2\\resources\\js\\routes\\admin\\api\\attendance\\op-month\\index.ts", "source_location": "L8"}, {"caller_nid": "op_month_index_currentform", "callee": "url", "is_member_call": true, "source_file": "D:\\office\\VASP_CRM_V2\\resources\\js\\routes\\admin\\api\\attendance\\op-month\\index.ts", "source_location": "L51"}, {"caller_nid": "op_month_index_resolve", "callee": "url", "is_member_call": true, "source_file": "D:\\office\\VASP_CRM_V2\\resources\\js\\routes\\admin\\api\\attendance\\op-month\\index.ts", "source_location": "L86"}, {"caller_nid": "op_month_index_resolveform", "callee": "url", "is_member_call": true, "source_file": "D:\\office\\VASP_CRM_V2\\resources\\js\\routes\\admin\\api\\attendance\\op-month\\index.ts", "source_location": "L129"}]}