{
  "holidays": [
    { "date": "2026-01-01", "name": "New Year's Day", "type": "national" },
    { "date": "2026-01-14", "name": "Magh Bihu", "type": "state" },
    { "date": "2026-01-15", "name": "Magh Bihu", "type": "state" },
    { "date": "2026-01-26", "name": "Republic Day", "type": "national" },
    { "date": "2026-03-03", "name": "Holi", "type": "national" },
    { "date": "2026-03-04", "name": "Holi", "type": "national" },
    { "date": "2026-03-21", "name": "Id-ul-Fitr", "type": "national" },
    { "date": "2026-04-14", "name": "Bohag Bihu", "type": "state" },
    { "date": "2026-04-15", "name": "Bohag Bihu", "type": "state" },
    { "date": "2026-04-16", "name": "Bohag Bihu", "type": "state" },
    { "date": "2026-05-27", "name": "Id-ul-Zuha (Bakrid)", "type": "national" },
    { "date": "2026-08-15", "name": "Independence Day", "type": "national" },
    { "date": "2026-10-02", "name": "Gandhi Jayanti", "type": "national" },
    { "date": "2026-10-19", "name": "Durga Puja", "type": "state" },
    { "date": "2026-10-20", "name": "Durga Puja", "type": "state" },
    { "date": "2026-10-21", "name": "Durga Puja", "type": "state" },
    { "date": "2026-11-08", "name": "Diwali", "type": "national" },
    { "date": "2026-12-25", "name": "Christmas Day", "type": "national" }
  ],
  "year": 2026
}
